infinianalytics/__init__.py
infinianalytics/register.py
infinianalytics-0.1.9.dist-info/LICENSE
infinianalytics-0.1.9.dist-info/METADATA
infinianalytics-0.1.9.dist-info/WHEEL
infinianalytics-0.1.9.dist-info/top_level.txt
infinianalytics-0.1.9.dist-info/RECORD
