Metadata-Version: 2.2
Name: infinianalytics
Version: 0.1.9
Summary: Librería para registrar eventos en la API de InfiniAnalytics
Author: Infini Analytics
Author-email: analytics@infini.es
Requires-Python: >=3.7
License-File: LICENSE
Requires-Dist: requests>=2.32.3
Dynamic: author
Dynamic: author-email
Dynamic: description
Dynamic: description-content-type
Dynamic: requires-dist
Dynamic: requires-python
Dynamic: summary
